assimilator/__init__.py
assimilator/alchemy/__init__.py
assimilator/alchemy/database/__init__.py
assimilator/alchemy/database/error_wrapper.py
assimilator/alchemy/database/model_utils.py
assimilator/alchemy/database/repository.py
assimilator/alchemy/database/unit_of_work.py
assimilator/alchemy/database/specifications/__init__.py
assimilator/alchemy/database/specifications/filtering_options.py
assimilator/alchemy/database/specifications/specifications.py
assimilator/alchemy/events/__init__.py
assimilator/alchemy/events/outbox_relay.py
assimilator/alchemy/events/database/__init__.py
assimilator/alchemy/events/database/repository.py
assimilator/core/__init__.py
assimilator/core/exceptions.py
assimilator/core/database/__init__.py
assimilator/core/database/exceptions.py
assimilator/core/database/models.py
assimilator/core/database/repository.py
assimilator/core/database/unit_of_work.py
assimilator/core/database/specifications/__init__.py
assimilator/core/database/specifications/adaptive.py
assimilator/core/database/specifications/filtering_options.py
assimilator/core/database/specifications/specifications.py
assimilator/core/database/specifications/types.py
assimilator/core/events/__init__.py
assimilator/core/events/events.py
assimilator/core/events/events_bus.py
assimilator/core/events/exceptions.py
assimilator/core/events/outbox_relay.py
assimilator/core/patterns/__init__.py
assimilator/core/patterns/context_managers.py
assimilator/core/patterns/error_wrapper.py
assimilator/core/patterns/lazy_command.py
assimilator/core/services/__init__.py
assimilator/core/services/base.py
assimilator/core/services/crud.py
assimilator/core/usability/__init__.py
assimilator/core/usability/exceptions.py
assimilator/core/usability/pattern_creator.py
assimilator/core/usability/registry.py
assimilator/internal/__init__.py
assimilator/internal/database/__init__.py
assimilator/internal/database/error_wrapper.py
assimilator/internal/database/models_utils.py
py_assimilator-1.3.1.dist-info/METADATA
py_assimilator-1.3.1.dist-info/WHEEL
py_assimilator-1.3.1.dist-info/licenses/LICENSE.md
py_assimilator-1.3.1.dist-info/RECORD
