Metadata-Version: 2.1
Name: py_assimilator
Version: 1.3.1
Summary: The best Domain-driven design patterns for your projects
Project-URL: Documentation, https://knucklesuganda.github.io/py_assimilator/
Project-URL: Github, https://github.com/knucklesuganda/py_assimilator/
Project-URL: Youtube RU, https://www.youtube.com/channel/UCSNpJHMOU7FqjD4Ttux0uuw
Project-URL: Youtube ENG, https://www.youtube.com/channel/UCeC9LNDwRP9OfjyOFHaSikA
Author-email: Andrey Ivanov <python.on.papyrus@gmail.com>
Maintainer-email: Andrey Ivanov <python.on.papyrus@gmail.com>
License-Expression: MIT
License-File: LICENSE.md
Keywords: Architecture,Backend,DDD,Database,Domain-driven design,Events,Patterns
Classifier: Development Status :: 5 - Production/Stable
Classifier: Environment :: Web Environment
Classifier: Intended Audience :: Developers
Classifier: Intended Audience :: Education
Classifier: Intended Audience :: Information Technology
Classifier: Intended Audience :: Science/Research
Classifier: Intended Audience :: System Administrators
Classifier: License :: OSI Approved :: MIT License
Classifier: Operating System :: OS Independent
Classifier: Programming Language :: Python
Classifier: Programming Language :: Python :: 3
Classifier: Programming Language :: Python :: 3 :: Only
Classifier: Programming Language :: Python :: 3.8
Classifier: Programming Language :: Python :: 3.9
Classifier: Programming Language :: Python :: 3.10
Classifier: Programming Language :: Python :: 3.11
Classifier: Topic :: Database
Classifier: Topic :: Internet
Classifier: Topic :: Software Development
Classifier: Topic :: Software Development :: Libraries
Classifier: Topic :: Software Development :: Libraries :: Application Frameworks
Classifier: Topic :: Software Development :: Libraries :: Python Modules
Classifier: Topic :: Software Development :: Testing :: Acceptance
Classifier: Topic :: Software Development :: Testing :: Unit
Classifier: Typing :: Typed
Requires-Python: >=3.8
Requires-Dist: pydantic<2.0.0,>=1.6.2
Provides-Extra: alchemy
Requires-Dist: sqlalchemy>=2.0.0; extra == 'alchemy'
Provides-Extra: kafka
Requires-Dist: kafka-python>=2.0.2; extra == 'kafka'
Provides-Extra: mongo
Requires-Dist: pymongo>=4.3.3; extra == 'mongo'
Provides-Extra: redis
Requires-Dist: redis>=4.4.0; extra == 'redis'
